web_pdb/__init__.py
web_pdb/buffer.py
web_pdb/web_console.py
web_pdb/wsgi_app.py
web_pdb/static/bundle.min.js
web_pdb/static/bundle.min.js.LICENSE.txt
web_pdb/static/styles.min.css
web_pdb/static/fonts/glyphicons-halflings-regular.eot
web_pdb/static/fonts/glyphicons-halflings-regular.svg
web_pdb/static/fonts/glyphicons-halflings-regular.ttf
web_pdb/static/fonts/glyphicons-halflings-regular.woff
web_pdb/static/fonts/glyphicons-halflings-regular.woff2
web_pdb/static/img/debug.png
web_pdb/static/img/debug.svg
web_pdb/templates/index.html
web_pdb-1.6.3.dist-info/LICENSE.txt
web_pdb-1.6.3.dist-info/METADATA
web_pdb-1.6.3.dist-info/WHEEL
web_pdb-1.6.3.dist-info/top_level.txt
web_pdb-1.6.3.dist-info/RECORD
