Metadata-Version: 2.1
Name: web-pdb
Version: 1.6.3
Summary: Web interface for Python's built-in PDB debugger
Home-page: https://github.com/romanvm/python-web-pdb
Author: Roman Miroshnychenko
Author-email: roman1972@gmail.com
License: MIT License
Keywords: pdb remote web debugger'
Platform: any
Classifier: Development Status :: 5 - Production/Stable
Classifier: Environment :: Web Environment
Classifier: Framework :: Bottle
Classifier: Intended Audience :: Developers
Classifier: License :: OSI Approved :: MIT License
Classifier: Operating System :: OS Independent
Classifier: Programming Language :: Python
Classifier: Programming Language :: Python :: 3
Classifier: Topic :: Software Development :: Debuggers
Requires-Python: >=3.6
License-File: LICENSE.txt
Requires-Dist: bottle>=0.12.25
Requires-Dist: asyncore-wsgi>=0.0.11
